cofr/__init__.py
cofr/cli.py
cofr/exceptions.py
cofr/store.py
cofr-1.0.0b2.dist-info/DESCRIPTION.rst
cofr-1.0.0b2.dist-info/METADATA
cofr-1.0.0b2.dist-info/RECORD
cofr-1.0.0b2.dist-info/WHEEL
cofr-1.0.0b2.dist-info/entry_points.txt
cofr-1.0.0b2.dist-info/metadata.json
cofr-1.0.0b2.dist-info/top_level.txt
