Metadata-Version: 2.0
Name: cofr
Version: 1.0.0b2
Summary: Make secure backups of sensitive data using your Trezor hardware wallet.
Home-page: https://github.com/thibault/cofr
Author: Thibault Jouannic
Author-email: thibault@miximum.fr
License: MIT
Platform: any
Classifier: Development Status :: 4 - Beta
Classifier: Environment :: Console
Classifier: License :: OSI Approved :: MIT License
Classifier: Operating System :: POSIX
Classifier: Operating System :: MacOS
Classifier: Operating System :: Unix
Classifier: Operating System :: Microsoft :: Windows
Classifier: Programming Language :: Python
Classifier: Programming Language :: Python :: 3
Requires-Python: >=3.5
Requires-Dist: cryptography
Requires-Dist: readline
Requires-Dist: trezor
Requires-Dist: click
